n2yo/__init__.py
n2yo/n2yo.py
n2yo/satellite_categories.py
n2yo_api-0.1.3.dist-info/LICENSE
n2yo_api-0.1.3.dist-info/METADATA
n2yo_api-0.1.3.dist-info/WHEEL
n2yo_api-0.1.3.dist-info/top_level.txt
n2yo_api-0.1.3.dist-info/RECORD
