Metadata-Version: 2.1
Name: n2yo-api
Version: 0.1.3
Summary: Python wrapper for the N2YO API.
Home-page: https://github.com/facorazza/n2yo-api
Author: F. A. Corazza
Author-email: federico.corazza@live.it
License: UNKNOWN
Platform: UNKNOWN
Classifier: Programming Language :: Python :: 3
Classifier: License :: OSI Approved :: MIT License
Classifier: Operating System :: OS Independent
Requires-Dist: requests
